aibooster/__init__.py
aibooster/observability/__init__.py
aibooster/observability/nccl_benchmark_torch/__init__.py
aibooster/observability/nccl_benchmark_torch/run.py
aibooster/observability/nccl_pattern_analyzer/__init__.py
aibooster/observability/nccl_pattern_analyzer/run.py
aibooster/intelligence/__init__.py
aibooster/intelligence/zenith_tune/command.py
aibooster/intelligence/zenith_tune/utils.py
aibooster/intelligence/zenith_tune/__init__.py
aibooster/intelligence/zenith_tune/distributed.py
aibooster/intelligence/zenith_tune/tuners/command_output.py
aibooster/intelligence/zenith_tune/tuners/command_runtime.py
aibooster/intelligence/zenith_tune/tuners/function_runtime.py
aibooster/intelligence/zenith_tune/tuners/__init__.py
aibooster/intelligence/zenith_tune/tuners/general.py
aibooster/intelligence/zenith_tune/tuners/command_executor.py
aibooster/intelligence/zenith_tune/tuning_component/__init__.py
aibooster/intelligence/zenith_tune/tuning_component/dataloader_affinity.py
aibooster/intelligence/zenith_tune/tuning_component/cpu_affinity.py
aibooster/intelligence/zenith_tune/tuning_component/limited_sampler.py
aibooster/intelligence/zenith_tune/integration/__init__.py
aibooster/intelligence/zenith_tune/integration/kubernetes/pytorchjob_tuning_scheduler.py
aibooster/intelligence/zenith_tune/integration/kubernetes/pytorchjob_tuner.py
aibooster/intelligence/zenith_tune/integration/kubernetes/annotation_based_tuning.py
aibooster/intelligence/zenith_tune/integration/kubernetes/__init__.py
aibooster/intelligence/zenith_tune/integration/kubernetes/pytorchjob.py
aibooster/intelligence/zenith_tune/integration/opentelemetry/__init__.py
aibooster/intelligence/zenith_tune/integration/opentelemetry/callback.py
aibooster/intelligence/zenith_tune/integration/mmengine/__init__.py
aibooster/intelligence/zenith_tune/integration/mmengine/registry.py
aibooster/intelligence/zenith_tune/integration/aibooster/__init__.py
aibooster-0.4.0.dist-info/METADATA
aibooster-0.4.0.dist-info/WHEEL
aibooster-0.4.0.dist-info/top_level.txt
aibooster-0.4.0.dist-info/RECORD
